factorial_aivn/__init__.py
factorial_aivn/app.py
factorial_aivn/factorial.py
factorial_aivn-0.1.2.dist-info/METADATA
factorial_aivn-0.1.2.dist-info/WHEEL
factorial_aivn-0.1.2.dist-info/RECORD
